tests
wikipedia
