Metadata-Version: 1.0
Name: wikipedia
Version: 0.9.4
Summary: Wikipedia API for Python
Home-page: https://github.com/goldsmith/Wikipedia
Author: Jonathan Goldsmith
Author-email: jhghank@gmail.com
License: MIT
Keywords: python wikipedia API
Platform: UNKNOWN
Classifier: Development Status :: 3 - Alpha
Classifier: Topic :: Software Development :: Libraries
Classifier: License :: OSI Approved :: MIT License
